convertToDecimalTime.py
convertToDecimalTime-1.0.2.dist-info/LICENSE
convertToDecimalTime-1.0.2.dist-info/METADATA
convertToDecimalTime-1.0.2.dist-info/WHEEL
convertToDecimalTime-1.0.2.dist-info/top_level.txt
convertToDecimalTime-1.0.2.dist-info/RECORD
