Metadata-Version: 2.1
Name: convertToDecimalTime
Version: 1.0.2
Summary: A small python library to convert standard time to decimal time.
Author-email: Apostolos Halis <tolishalis@gmail.com>
Project-URL: Homepage, https://github.com/TolisSth/convertToDecimalTime
Project-URL: Issues, https://github.com/TolisSth/convertToDecimalTime/issues
Classifier: Programming Language :: Python :: 3
Classifier: License :: OSI Approved :: MIT License
Classifier: Operating System :: OS Independent
Requires-Python: >=3.8
License-File: LICENSE
